sadra_tse/__init__.py
sadra_tse-1.0.0.dist-info/LICENSE.txt
sadra_tse-1.0.0.dist-info/METADATA
sadra_tse-1.0.0.dist-info/WHEEL
sadra_tse-1.0.0.dist-info/top_level.txt
sadra_tse-1.0.0.dist-info/RECORD
