Metadata-Version: 2.1
Name: sadra_tse
Version: 1.0.0
Summary: A Python Module to Access Tehran Stock Exchange Historical and Real-Time Data
Author: Dr.Amirsadra Akbari
Author-email: amirsadra.akbari@iau.ir
License: BSD (3-clause)
License-File: LICENSE.txt
Requires-Dist: requests
Requires-Dist: jdatetime
Requires-Dist: pandas
Requires-Dist: numpy
Requires-Dist: bs4
Requires-Dist: asyncio
Requires-Dist: urllib3
Requires-Dist: aiohttp
Requires-Dist: unsync
Requires-Dist: IPython
Requires-Dist: persiantools
Requires-Dist: datetime
Requires-Dist: XlsxWriter
Requires-Dist: lxml
